uznltk/__init__.py
uznltk/_clean.py
uznltk/_download.py
uznltk/_lemmatizer.py
uznltk/_stem.py
uznltk/_stop_words.py
uznltk/_syllable.py
uznltk/_tokenizer.py
uznltk-0.0.11.dist-info/licenses/LICENSE
uznltk-0.0.11.dist-info/METADATA
uznltk-0.0.11.dist-info/WHEEL
uznltk-0.0.11.dist-info/top_level.txt
uznltk-0.0.11.dist-info/RECORD
