Metadata-Version: 2.4
Name: uznltk
Version: 0.0.11
Summary: The Uzbek Natural Language Toolkit (NLTK) is a Python package for natural language processing.
Home-page: https://github.com/UlugbekSalaev/uznltk
Author: Ulugbek Salaev
Author-email: ulugbek0302@gmail.com
License: MIT
Project-URL: Bug Tracker, https://github.com/UlugbekSalaev/uznltk/issues
Keywords: nltk,morphology,uzbek-language,pos tagging,morphological tagging
Classifier: Programming Language :: Python :: 3
Classifier: License :: OSI Approved :: MIT License
Classifier: Operating System :: OS Independent
Requires-Python: >=3.7
License-File: LICENSE
Requires-Dist: requests
Requires-Dist: UzMorphAnalyser
Requires-Dist: UzSyllable
Dynamic: author
Dynamic: author-email
Dynamic: classifier
Dynamic: description
Dynamic: description-content-type
Dynamic: home-page
Dynamic: keywords
Dynamic: license
Dynamic: license-file
Dynamic: project-url
Dynamic: requires-dist
Dynamic: requires-python
Dynamic: summary
